gym_anm/__init__.py
gym_anm/agents/__init__.py
gym_anm/agents/mpc.py
gym_anm/agents/mpc_constant.py
gym_anm/agents/mpc_perfect.py
gym_anm/envs/__init__.py
gym_anm/envs/anm6_env/__init__.py
gym_anm/envs/anm6_env/anm6.py
gym_anm/envs/anm6_env/anm6_easy.py
gym_anm/envs/anm6_env/network.py
gym_anm/envs/anm6_env/rendering/__init__.py
gym_anm/envs/anm6_env/rendering/css/styles.css
gym_anm/envs/anm6_env/rendering/envs/anm6/network.svg
gym_anm/envs/anm6_env/rendering/envs/anm6/svgLabels.js
gym_anm/envs/anm6_env/rendering/index.html
gym_anm/envs/anm6_env/rendering/js/dateTime.js
gym_anm/envs/anm6_env/rendering/js/devices.js
gym_anm/envs/anm6_env/rendering/js/graph.js
gym_anm/envs/anm6_env/rendering/js/init.js
gym_anm/envs/anm6_env/rendering/js/reward.js
gym_anm/envs/anm6_env/rendering/js/text.js
gym_anm/envs/anm6_env/rendering/py/__init__.py
gym_anm/envs/anm6_env/rendering/py/constants.py
gym_anm/envs/anm6_env/rendering/py/rendering.py
gym_anm/envs/anm6_env/rendering/py/servers.py
gym_anm/envs/anm6_env/utils.py
gym_anm/envs/anm_env.py
gym_anm/envs/utils.py
gym_anm/errors.py
gym_anm/simulator/__init__.py
gym_anm/simulator/check_network.py
gym_anm/simulator/components/__init__.py
gym_anm/simulator/components/branch.py
gym_anm/simulator/components/bus.py
gym_anm/simulator/components/constants.py
gym_anm/simulator/components/devices.py
gym_anm/simulator/components/errors.py
gym_anm/simulator/simulator.py
gym_anm/simulator/solve_load_flow.py
gym_anm/utils.py
gym_anm-2.0.1.dist-info/LICENSE.md
gym_anm-2.0.1.dist-info/METADATA
gym_anm-2.0.1.dist-info/WHEEL
gym_anm-2.0.1.dist-info/RECORD
