Metadata-Version: 2.1
Name: gym-anm
Version: 2.0.1
Summary: A framework to build Reinforcement Learning environments for Active Network Management tasks in electricity networks.
Home-page: https://github.com/robinhenry/gym-anm
License: MIT
Author: Robin Henry
Author-email: robin@robinxhenry.com
Requires-Python: >=3.10,<4.0
Classifier: License :: OSI Approved :: MIT License
Classifier: Programming Language :: Python :: 3
Classifier: Programming Language :: Python :: 3.10
Classifier: Programming Language :: Python :: 3.11
Classifier: Programming Language :: Python :: 3.12
Classifier: Programming Language :: Python :: 3.13
Requires-Dist: cvxpy (>=1.2.2,<2.0.0)
Requires-Dist: gymnasium (>=1.0.0,<2.0.0)
Requires-Dist: numpy (>=2.1,<3.0)
Requires-Dist: pandas (>=2.0,<3.0)
Requires-Dist: requests (>=2.28.1,<3.0.0)
Requires-Dist: websocket-client (==0.56.0)
Requires-Dist: websocket-server (==0.4)
Project-URL: Documentation, https://gym-anm.readthedocs.io/en/latest/
Project-URL: Repository, https://github.com/robinhenry/gym-anm
